forwardkinematics/__init__.py
forwardkinematics/fksCommon/fk.py
forwardkinematics/planarFks/planarArmFk.py
forwardkinematics/planarFks/planar_fk.py
forwardkinematics/planarFks/point_fk.py
forwardkinematics/urdfFks/casadiConversion/__init__.py
forwardkinematics/urdfFks/casadiConversion/geometry/__init__.py
forwardkinematics/urdfFks/casadiConversion/geometry/transformation_matrix.py
forwardkinematics/urdfFks/casadiConversion/urdfparser.py
forwardkinematics/urdfFks/generic_urdf_fk.py
forwardkinematics/urdfFks/urdfFk.py
forwardkinematics/xmlFks/generic_xml_fk.py
forwardkinematics-1.2.3.dist-info/METADATA
forwardkinematics-1.2.3.dist-info/WHEEL
forwardkinematics-1.2.3.dist-info/RECORD
