Metadata-Version: 2.1
Name: forwardkinematics
Version: 1.2.3
Summary: "Light-weight implementation of forward kinematics using casadi."
Home-page: https://github.com/maxspahn/forwardKinematics.git
License: MIT
Author: Max Spahn
Author-email: m.spahn@tudelft.nl
Requires-Python: >=3.8,<4.0
Classifier: License :: OSI Approved :: MIT License
Classifier: Programming Language :: Python :: 3
Classifier: Programming Language :: Python :: 3.8
Classifier: Programming Language :: Python :: 3.9
Classifier: Programming Language :: Python :: 3.10
Classifier: Programming Language :: Python :: 3.11
Classifier: Programming Language :: Python :: 3.12
Requires-Dist: casadi (>=3.5.4,<4.0.0,!=3.5.5.post1,!=3.5.5.post2)
Requires-Dist: numpy (>=1.15.3,<2.0.0)
Requires-Dist: urdf_parser_py (>=0.0.3)
Project-URL: Repository, https://github.com/maxspahn/forwardKinematics.git
